torch_vggish_yamnet/__init__.py
torch_vggish_yamnet/input_proc.py
torch_vggish_yamnet/params.py
torch_vggish_yamnet/vggish/__init__.py
torch_vggish_yamnet/vggish/model.py
torch_vggish_yamnet/yamnet/__init__.py
torch_vggish_yamnet/yamnet/model.py
torch_vggish_yamnet-0.2.1.dist-info/LICENSE
torch_vggish_yamnet-0.2.1.dist-info/METADATA
torch_vggish_yamnet-0.2.1.dist-info/WHEEL
torch_vggish_yamnet-0.2.1.dist-info/top_level.txt
torch_vggish_yamnet-0.2.1.dist-info/RECORD
