Metadata-Version: 2.1
Name: torch-vggish-yamnet
Version: 0.2.1
Summary: torch_vggish_yamnet: PyTorch VGGish & YAMNet models
Home-page: https://github.com/StefanoGiacomelli/torch_vggish_yamnet
Author: Stefano Giacomelli (Ph.D. student UnivAQ)
Author-email: stefano.giacomelli@graduate.univaq.it
Classifier: Programming Language :: Python :: 3
Classifier: License :: OSI Approved :: MIT License
Classifier: Operating System :: OS Independent
Requires-Python: >=3.6
License-File: LICENSE
Requires-Dist: numpy
Requires-Dist: torch
Requires-Dist: torchaudio
